pycea/__init__.py
pycea/utils.py
pycea/datasets/__init__.py
pycea/datasets/datasets.py
pycea/get/__init__.py
pycea/get/df.py
pycea/get/leaves.py
pycea/get/palette.py
pycea/get/root.py
pycea/pl/__init__.py
pycea/pl/_docs.py
pycea/pl/_handlers.py
pycea/pl/_legend.py
pycea/pl/_utils.py
pycea/pl/plot_n_extant.py
pycea/pl/plot_tree.py
pycea/pp/__init__.py
pycea/pp/setup_tree.py
pycea/tl/__init__.py
pycea/tl/_aggregators.py
pycea/tl/_metrics.py
pycea/tl/_utils.py
pycea/tl/ancestral_states.py
pycea/tl/autocorr.py
pycea/tl/clades.py
pycea/tl/distance.py
pycea/tl/fitness.py
pycea/tl/n_extant.py
pycea/tl/neighbor_distance.py
pycea/tl/partition_test.py
pycea/tl/sort.py
pycea/tl/topology.py
pycea/tl/tree_distance.py
pycea/tl/tree_neighbors.py
pycea_lineage-0.2.0.dist-info/METADATA
pycea_lineage-0.2.0.dist-info/WHEEL
pycea_lineage-0.2.0.dist-info/licenses/LICENSE
pycea_lineage-0.2.0.dist-info/RECORD
